rs_drift/__init__.py
rs_drift/drift.py
rs_drift/numba_drift.py
rs_drift/.ipynb_checkpoints/drift-checkpoint.py
rs_drift/data/test_data.csv
rs_drift-1.2.2.dist-info/METADATA
rs_drift-1.2.2.dist-info/WHEEL
rs_drift-1.2.2.dist-info/licenses/LICENSE
rs_drift-1.2.2.dist-info/RECORD
