Metadata-Version: 2.4
Name: rs_drift
Version: 1.2.2
Summary: tool to reconstruct radiosonde trajectories
Project-URL: Homepage, https://gitlab.phaidra.org/imgw/rs_drift
Author-email: Ulrich Voggenberger <ulrich.voggenberger@unvie.ac.at>
License-File: LICENSE
Classifier: License :: OSI Approved :: MIT License
Classifier: Operating System :: OS Independent
Classifier: Programming Language :: Python :: 3
Requires-Python: >=3.7
